labcast/metadata.py
labcast/cli/__init__.py
labcast-0.0.1.dist-info/METADATA
labcast-0.0.1.dist-info/WHEEL
labcast-0.0.1.dist-info/entry_points.txt
labcast-0.0.1.dist-info/RECORD
