Metadata-Version: 2.4
Name: labcast
Version: 0.0.1
Summary: A GitLab-to-GitLab CI connector
Project-URL: Source, https://gitlab.com/ambhora/software/labcast
Author-email: Jayesh Badwaik <jayesh@ambhora.com>
License-Expression: Apache-2.0
Requires-Dist: livereload
Requires-Dist: pyyaml
Requires-Dist: ruamel-yaml>=0.18
Requires-Dist: semver
